LICENSE
requirements-dev.txt
requirements.txt
mingdongtextsim/__init__.py
mingdongtextsim/similarity.py
mingdongtextsim/vector.py
mingdongtextsim/version.py
mingdongtextsim/algorithm/__init__.py
mingdongtextsim/algorithm/distance.py
mingdongtextsim/algorithm/rank_bm25.py
mingdongtextsim/bert/__init__.py
mingdongtextsim/bert/extract_feature.py
mingdongtextsim/bert/graph.py
mingdongtextsim/bert/model.py
mingdongtextsim/bert/modeling.py
mingdongtextsim/bert/optimization.py
mingdongtextsim/bert/predict.py
mingdongtextsim/bert/tokenization.py
mingdongtextsim/bert/train.py
mingdongtextsim/embeddings/__init__.py
mingdongtextsim/embeddings/bert_embedding.py
mingdongtextsim/embeddings/embedding.py
mingdongtextsim/embeddings/word_embedding.py
mingdongtextsim/processors/__init__.py
mingdongtextsim/processors/base_processor.py
mingdongtextsim/processors/default_processor.py
mingdongtextsim/utils/__init__.py
mingdongtextsim/utils/get_file.py
mingdongtextsim/utils/logger.py
mingdongtextsim/utils/ngram.py
mingdongtextsim/utils/non_masking_layer.py
mingdongtextsim/utils/timer.py
mingdongtextsim/utils/tokenizer.py
mingdongtextsim-0.1.5.dist-info/LICENSE
mingdongtextsim-0.1.5.dist-info/METADATA
mingdongtextsim-0.1.5.dist-info/WHEEL
mingdongtextsim-0.1.5.dist-info/top_level.txt
mingdongtextsim-0.1.5.dist-info/RECORD
